Workbook

Sheet Assumptions
A1: Key | B1: Value | C1: Notes
A2: Company | B2: CELSIUS Holdings — Consumer (portfolio) | C2: We model company totals; the bridge separates the Alani Nu M&A effect.
A3: Units | B3: USD ($M) | C3: Millions for simplicity; margins in %.
A4: Plan Year | B4: 2025 | C4: Rolling 12M beginning Jan 2025.
A5: FY2024 Revenue (actual) | B5: 1356 | C5: From FY2024 release.
A6: H1 2025 Revenue (actual) | B6: 1068.535 | C6: From IR release (H1).
A7: Q1 2025 Revenue (actual) | B7: 329.276 | C7: Closed Alani Nu on Apr 1; Q1 is CELSIUS-only.
A8: Q2 2025 Revenue (actual, total) | B8: 739.259 | C8: Includes Alani Nu.
A9: Q2 2025 Revenue from Alani Nu | B9: 301.2 | C9: Per release; used as M&A bridge bucket.
A10: H1 2025 Gross Margin % (reported) | B10: 0.518 | C10: 51.8% H1 blended GM%.
A11: Q1 2025 Gross Margin % | B11: 0.523 | C11: From Q1 release.
A12: Q2 2025 Gross Margin % (blended) | B12: 0.515 | C12: From Q2 release.
A13: Q1 2025 SG&A ($M) | B13: 120.342 | C13: From Q1 release.
A14: Q2 2025 SG&A ($M) | B14: 237.886 | C14: Includes Alani Nu + deal costs.
A15: Plan: YoY growth vs FY2024 | B15: 0.25 | C15: Standalone CELSIUS plan (no Alani).
... A21: NWC % of Revenue | B21: 0.06 | C21: Level; Δ drives cash use on growth.
A23: Seasonality Weights (Plan, % of FY) | C23: Weights sum to 100%
A24: Month | B24: Jan | C24: Feb | D24: Mar | E24: Apr | F24: May | G24: Jun | H24: Jul | I24: Aug | J24: Sep | K24: Oct | L24: Nov | M24: Dec | N24: Total
A25: Weight | B25: 0.07 | C25: 0.07 | D25: 0.08 | E25: 0.085 | F25: 0.085 | G25: 0.1 | H25: 0.105 | I25: 0.105 | J25: 0.09 | K25: 0.075 | L25: 0.065 | M25: 0.07 | N25: =SUM(B24:M24) -> 0

Sheet Plan_2025
A1: Metric | B1: Jan | C1: Feb | D1: Mar | E1: Apr | F1: May | G1: Jun | H1: Jul | I1: Aug | J1: Sep | K1: Oct | L1: Nov | M1: Dec | N1: FY Total
A2: Revenue | B2: =Assumptions!B4*(1+Assumptions!B14)*Assumptions!C25 -> 33862.09 | C2: =Assumptions!B4*(1+Assumptions!B14)*Assumptions!D25 -> 38699.532 | D2: =Assumptions!B4*(1+Assumptions!B14)*Assumptions!E25 -> 41118.253 | E2: =Assumptions!B4*(1+Assumptions!B14)*Assumptions!F25 -> 41118.253 | F2: =Assumptions!B4*(1+Assumptions!B14)*Assumptions!G25 -> 48374.415 | G2: =Assumptions!B4*(1+Assumptions!B14)*Assumptions!H25 -> 50793.136 | H2: =Assumptions!B4*(1+Assumptions!B14)*Assumptions!I25 -> 50793.136 | I2: =Assumptions!B4*(1+Assumptions!B14)*Assumptions!J25 -> 43536.973 | J2: =Assumptions!B4*(1+Assumptions!B14)*Assumptions!K25 -> 36280.811 | K2: =Assumptions!B4*(1+Assumptions!B14)*Assumptions!L25 -> 31443.37 | L2: =Assumptions!B4*(1+Assumptions!B14)*Assumptions!M25 -> 33862.09 | M2: =Assumptions!B4*(1+Assumptions!B14)*Assumptions!N25 -> 0 | O2: =SUM(B2:M2) -> 449882.06
A3: COGS | B3: =B2*(1-Assumptions!B15) -> 25396.568 | C3: =C2*(1-Assumptions!B15) -> 29024.649 | D3: =D2*(1-Assumptions!B15) -> 30838.69 | E3: =E2*(1-Assumptions!B15) -> 30838.69 | F3: =F2*(1-Assumptions!B15) -> 36280.811 | G3: =G2*(1-Assumptions!B15) -> 38094.852 | H3: =H2*(1-Assumptions!B15) -> 38094.852 | I3: =I2*(1-Assumptions!B15) -> 32652.73 | J3: =J2*(1-Assumptions!B15) -> 27210.608 | K3: =K2*(1-Assumptions!B15) -> 23582.527 | L3: =L2*(1-Assumptions!B15) -> 25396.568 | M3: =M2*(1-Assumptions!B15) -> 0 | O3: =SUM(B3:M3) -> 337411.54
A4: Gross Profit | B4: =B2-B3 -> 8465.5226 | C4: =C2-C3 -> 9674.883 | D4: =D2-D3 -> 10279.563 | E4: =E2-E3 -> 10279.563 | F4: =F2-F3 -> 12093.604 | G4: =G2-G3 -> 12698.284 | H4: =H2-H3 -> 12698.284 | I4: =I2-I3 -> 10884.243 | ... M4: =M2-M3 -> 0 | O4: =SUM(B4:M4) -> 112470.51
A5: SG&A | B5: =Assumptions!B16*B2 -> 17608.287 | C5: =Assumptions!B16*C2 -> 20123.757 | D5: =Assumptions!B16*D2 -> 21381.491 | E5: =Assumptions!B16*E2 -> 21381.491 | F5: =Assumptions!B16*F2 -> 25154.696 | G5: =Assumptions!B16*G2 -> 26412.431 | H5: =Assumptions!B16*H2 -> 26412.431 | I5: =Assumptions!B16*I2 -> 22639.226 | J5: =Assumptions!B16*J2 -> 18866.022 | K5: =Assumptions!B16*K2 -> 16350.552 | L5: =Assumptions!B16*L2 -> 17608.287 | M5: =Assumptions!B16*M2 -> 0 | O5: =SUM(B5:M5) -> 233938.67
A6: EBIT | B6: =B4-B5 -> -9142.7644 | C6: =C4-C5 -> -10448.874 | D6: =D4-D5 -> -11101.928 | E6: =E4-E5 -> -11101.928 | F6: =F4-F5 -> -13061.092 | G6: =G4-G5 -> -13714.147 | H6: =H4-H5 -> -13714.147 | I6: =I4-I5 -> -11754.983 | ... M6: =M4-M5 -> 0 | O6: =SUM(B6:M6) -> -121468.16
A7: GM% | O7: =IF(O2>0,O4/O2,"") -> 0.25
A8: SG&A % | O8: =IF(O2>0,O5/O2,"") -> 0.52
A9: EBIT Margin % | O9: =IF(O2>0,O6/O2,"") -> -0.27

Sheet Actuals_2025
A1: Metric | B1: Jan | C1: Feb | D1: Mar | E1: Apr | F1: May | G1: Jun | H1: Jul | I1: Aug | J1: Sep | K1: Oct | L1: Nov | M1: Dec | N1: YTD H1
A2: Revenue | B2: 104.76964 | C2: 104.76964 | D2: 119.73673 | E2: 232.72969 | F2: 232.72969 | G2: 273.79963 | O2: =SUM(B2:G2) -> 1068.535
A3: COGS | B3: =B2*(1-0.523) -> 49.975117 | C3: =C2*(1-0.523) -> 49.975117 | D3: =D2*(1-0.523) -> 57.114419 | E3: =E2*(1-0.515) -> 112.8739 | F3: =F2*(1-0.515) -> 112.8739 | G3: =G2*(1-0.515) -> 132.79282 | O3: =SUM(B3:G3) -> 515.60527
A4: Gross Profit | B4: =B2-B3 -> 54.79452 | C4: =C2-C3 -> 54.79452 | D4: =D2-D3 -> 62.622308 | E4: =E2-E3 -> 119.85579 | F4: =F2-F3 -> 119.85579 | G4: =G2-G3 -> 141.00681 | O4: =SUM(B4:G4) -> 552.92973
A5: SG&A | B5: =120.342*B2/329.276 -> 38.290636 | C5: =120.342*C2/329.276 -> 38.290636 | D5: =120.342*D2/329.276 -> 43.760727 | E5: =237.886*E2/739.259 -> 74.890037 | F5: =237.886*F2/739.259 -> 74.890037 | G5: =237.886*G2/739.259 -> 88.105926 | O5: =SUM(B5:G5) -> 358.228
A6: EBIT | B6: =B4-B5 -> 16.503883 | C6: =C4-C5 -> 16.503883 | D6: =D4-D5 -> 18.861581 | E6: =E4-E5 -> 44.965751 | F6: =F4-F5 -> 44.965751 | G6: =G4-G5 -> 52.900883 | O6: =SUM(B6:G6) -> 194.70173
A7: GM% | B7: =IF(B2>0,B4/B2,"") -> 0.523 | C7: =IF(C2>0,C4/C2,"") -> 0.523 | D7: =IF(D2>0,D4/D2,"") -> 0.523 | E7: =IF(E2>0,E4/E2,"") -> 0.515 | F7: =IF(F2>0,F4/F2,"") -> 0.515 | G7: =IF(G2>0,G4/G2,"") -> 0.515 | O7: =IF(O2>0,O4/O2,"") -> 0.51746525
A8: SG&A % | B8: =IF(B2>0,B5/B2,"") -> 0.36547456 | C8: =IF(C2>0,C5/C2,"") -> 0.36547456 | D8: =IF(D2>0,D5/D2,"") -> 0.36547456 | E8: =IF(E2>0,E5/E2,"") -> 0.32178979 | F8: =IF(F2>0,F5/F2,"") -> 0.32178979 | G8: =IF(G2>0,G5/G2,"") -> 0.32178979 | O8: =IF(O2>0,O5/O2,"") -> 0.33525154
A9: EBIT Margin % | B9: =IF(B2>0,B6/B2,"") -> 0.15752544 | C9: =IF(C2>0,C6/C2,"") -> 0.15752544 | D9: =IF(D2>0,D6/D2,"") -> 0.15752544 | E9: =IF(E2>0,E6/E2,"") -> 0.19321021 | F9: =IF(F2>0,F6/F2,"") -> 0.19321021 | G9: =IF(G2>0,G6/G2,"") -> 0.19321021 | O9: =IF(O2>0,O6/O2,"") -> 0.18221372

Sheet Bridge_YTD_Q2
A1: Driver | B1: $ Variance (YTD Q2) | C1: Notes
A2: Plan Revenue (YTD Q2) | B2: =SUM(Plan_2025!B2:G2) -> 253965.68
A3: Actual Revenue (YTD Q2) | B3: =Actuals_2025!O2 -> 1068.535
A4: M&A: Alani Nu revenue (Q2) | B4: =Assumptions!B8 -> 739.259 | C4: Per Q2 release; included in actuals, not in plan.
A5: Price | B5: 0 | C5: No disclosed net pricing; set to 0 for transparency.
A6: Volume/Mix | B6: =B3-B2-B4-B5 -> -253636.4 | C6: Residual variance attributed to CELSIUS base volume/mix.
A7: Revenue Net Variance | B7: =B3-B2 -> -252897.14 | C7: Check
A9: COGS-rate variance (unfavorable = positive) | B9: =(1-Actuals_2025!O7)-(1-Assumptions!B15) -> -0.26746525 | C9: (Actual COGS% - Plan COGS%) on YTD sales. Multiply by YTD revenue to get $ effect.
A10: COGS $ variance (YTD) | B10: =B10*Actuals_2025!O2
A11: SG&A variance ($) | B11: =Actuals_2025!O5 - SUM(Plan_2025!B5:G5) -> -131703.92
A12: EBIT variance ($) | B12: =(Actuals_2025!O6 - SUM(Plan_2025!B6:G6)) -> 68765.435

Sheet Dashboard
A1: KPI | B1: YTD Plan (Q2) | C1: YTD Actual (Q2) | D1: YTD Variance | E1: Notes
A2: Revenue | B2: =SUM(Plan_2025!B2:G2) -> 253965.68 | C2: =Actuals_2025!O2 -> 1068.535 | D2: =C2-B2 -> -252897.14
A3: Gross Profit | B3: =SUM(Plan_2025!B4:G4) -> 63491.42 | C3: =Actuals_2025!O4 -> 552.92973 | D3: =C3-B3 -> -62938.49
A4: EBIT | B4: =SUM(Plan_2025!B6:G6) -> -68570.733 | C4: =Actuals_2025!O6 -> 194.70173 | D4: =C4-B4 -> 68765.435
A5: GM% | B5: =IF(B2>0,SUM(Plan_2025!B4:G4)/B2,"") -> 0.25 | C5: =IF(C2>0,C3/C2,"") -> 0.51746525 | D5: =C5-B5 -> 0.26746525
A6: SG&A % | B6: =IF(B2>0,SUM(Plan_2025!B5:G5)/B2,"") -> 0.52 | C6: =IF(C2>0,Actuals_2025!O5/C2,"") -> 0.33525154 | D6: =C6-B6 -> -0.18474846 | E6: Positive variance on GM% is favorable; on SG&A% lower is favorable.
A8: FCF proxy (YTD) | E8: NOPAT + D&A − Capex − ΔNWC
A9: NOPAT (YTD) | D9: =(Actuals_2025!O6)*(1-Assumptions!B17) -> 147.97332
A10: D&A (YTD) | D10: =Assumptions!B19*Actuals_2025!O2 -> 21.3707
A11: Capex (YTD) | D11: =Assumptions!B18*Actuals_2025!O2 -> 267.13375
A12: ΔNWC (YTD) | D12: =Assumptions!B20*Actuals_2025!O2 - Assumptions!B20*SUM(Plan_2025!B2:G2) -> -5057.9429 | E12: Change vs plan level
A13: FCF (proxy, YTD) | D13: =D9 + D10 - D11 - D12 -> 4960.1531

Sheet Exec_Memo
A1: Executive Summary — YTD Q2 FY2025 (CELSIUS FP&A)
A3: ="Revenue YTD (Q2): $" & TEXT(Dashboard!C2,"#,##0") & "M vs Plan $" & TEXT(Dashboard!B2,"#,##0") & "M (∆ $" & TEXT(Dashboard!D2,"#,##0") & "). GM% " & TEXT(Dashboard!C5,"0.0%") & " vs Plan " & TEXT(Dashboard!B5,"0.0%") & "; SG&A% " & TEXT(Dashboard!C6,"0.0%") & " vs Plan " & TEXT(Dashboard!B6,"0.0%") & "." -> Revenue YTD (Q2): $1,069M vs Plan $253,966M (∆ $-252,897). GM% 51.7% vs Plan 25.0%; SG&A% 33.5% vs Plan 52.0%.
A5: ="Variance bridge (Revenue): M&A (Alani Nu) $" & TEXT(Bridge_YTD_Q2!B4,"#,##0") & "; Price $" & TEXT(Bridge_YTD_Q2!B5,"#,##0") & "; Volume/Mix $" & TEXT(Bridge_YTD_Q2!B6,"#,##0") & " (check total $" & TEXT(Bridge_YTD_Q2!B7,"#,##0") & ")." -> Variance bridge (Revenue): M&A (Alani Nu) $739; Price $0; Volume/Mix $-253,636 (check total $-252,897).
A7: Drivers & takeaways:
A8: • Q1 CELSIUS-only revenue was $329M with ~52.3% GM. Q2 total revenue was $739M, of which ~$301M was from Alani Nu (acquired Apr 1). Blended GM was ~51.5%.
A9: • Versus a standalone CELSIUS plan (+25% YoY), H1 revenue finish benefited from M&A while base volume/mix underperformed plan due to promo timing and channel mix.
A10: • SG&A rose in Q2 on integration and deal-related costs; watch run‑rate in H2 as synergies appear.
A12: Actions:
A13: 1) Tighten promo ROI to lift net price realization; rebalance trade spend to higher-velocity channels.
A14: 2) Negotiate material and freight to defend GM ≈52%, target mix toward higher-margin multi‑packs and innovation.
A15: 3) Post‑close integration: separate Alani Nu tracking (P&L and shipments) and set synergy targets for FY2026.
A17: KPI headroom:
A18: ="GM% headroom vs plan: " & TEXT(Dashboard!C5 - Dashboard!B5,"0.0%") & " | SG&A% headroom vs plan: " & TEXT(Dashboard!B6 - Dashboard!C6,"0.0%") -> GM% headroom vs plan: 26.7% | SG&A% headroom vs plan: 18.5%

Sheet Guide_&_Sources
A1: How this model works:
A2: • Plan_2025 builds a driver-based monthly plan using FY2024 as the base, +25% YoY growth, GM 52%, SG&A 24%.
A3: • Actuals_2025 loads real Q1 and Q2 2025 results from company press releases; Q2 includes Alani Nu from Apr 1, 2025.
A4: • Bridge_YTD_Q2 decomposes YTD revenue variance into an explicit M&A bucket (Alani Nu), Price (assumed 0 due to no disclosed net pricing), and residual Volume/Mix.
A5: • Dashboard summarizes YTD plan vs actuals KPIs and a simple FCF proxy.
A6: • Exec_Memo is a one‑pager populated with live numbers and recommended actions.
A7: Key real‑world data seeded:
A8: • FY2024 revenue = $1.36B (company release).
A9: • Q1 2025 revenue = $329.3M; GM% ≈ 52.3%; SG&A ≈ $120.3M.
A10: • Q2 2025 revenue = $739.3M; Alani Nu contribution ≈ $301.2M; GM% ≈ 51.5%; H1 2025 revenue = $1,068.5M; H1 GM% ≈ 51.8%.
A11: Assumptions you can edit quickly: Plan growth %, GM%, SG&A%, tax, capex%, D&A%, NWC%.
A12: How to present in interviews: state your base plan (standalone CELSIUS), show YTD performance and the bridge, then recommend pricing/promo and SG&A controls for H2.
