Workbook

Sheet Inputs
A1: Key | B1: Value | C1: Notes
A2: Company | B2: Robinhood Markets, Inc. (HOOD) | C2: Change if using another company
A3: Currency | B3: USD ($M) | C3: Model in millions
A4: Fiscal Start Year | B4: 905 | C4: Forecast FY2025–FY2029
A5: Diluted Shares (mm) | B5: -4300 | C5: Enter diluted share count
A6: Net Debt ($M) | B6: 0.25 | C6: Debt - Cash (negative = net cash)
A7: Tax Rate | B7: 0.12 | C7: Long-run effective tax rate
A8: WACC | B8: 0.03 | C8: Weighted Average Cost of Capital
A9: Terminal Growth (g) | B9: 2951 | C9: Perpetual growth after Year 5
A10: Starting Revenue ($M) | B10: 0.18 | C10: Last FY or TTM revenue to roll forward
A11: Revenue Growth Y1 | B11: 0.12 | C11: Year 1 growth
A12: Revenue Growth Y2 | B12: 0.1 | C12: Year 2 growth
A13: Revenue Growth Y3 | B13: 0.08 | C13: Year 3 growth
A14: Revenue Growth Y4 | B14: 0.06 | C14: Year 4 growth
A15: Revenue Growth Y5 | B15: 0.8 | C15: Year 5 growth
A16: Gross Margin % | B16: 0.22 | C16: Long-run gross margin
A17: S&M % of Rev | B17: 0.12
A18: R&D % of Rev | B18: 0.09
A19: G&A % of Rev | B19: 0.03
A20: D&A % of Rev | B20: 0.04
A21: Capex % of Rev | B21: 0.02
A22: NWC % of Rev | B22: 0.03 | C22: Working capital = % of revenue; ΔNWC drives cash outflow on growth

Sheet Forecast
A1: Metric | B1: Y1 | C1: Y2 | D1: Y3 | E1: Y4 | F1: Y5 | G1: Notes
A2: Revenue | B2: =Inputs!B9*(1+Inputs!B10) | C2: =B2*(1+Inputs!B11) | D2: =C2*(1+Inputs!B12) | E2: =D2*(1+Inputs!B13) | F2: =E2*(1+Inputs!B14) | G2: Revenues and costs in USD millions; FCFF used for DCF
A3: Revenue Growth % | B3: =IFERROR(B2/IF(A2>0,A2,NA())-1,"") | C3: =IFERROR(C2/IF(B2>0,B2,NA())-1,"") | D3: =IFERROR(D2/IF(C2>0,C2,NA())-1,"") | E3: =IFERROR(E2/IF(D2>0,D2,NA())-1,"") | F3: =IFERROR(F2/IF(E2>0,E2,NA())-1,"")
A4: COGS ($) | B4: =(1-Inputs!B15)*B2 | C4: =(1-Inputs!B15)*C2 | D4: =(1-Inputs!B15)*D2 | E4: =(1-Inputs!B15)*E2 | F4: =(1-Inputs!B15)*F2
A5: Gross Profit ($) | B5: =B2-B4 | C5: =C2-C4 | D5: =D2-D4 | E5: =E2-E4 | F5: =F2-F4
A6: S&M ($) | B6: =Inputs!B16*B2 | C6: =Inputs!B16*C2 | D6: =Inputs!B16*D2 | E6: =Inputs!B16*E2 | F6: =Inputs!B16*F2
A7: R&D ($) | B7: =Inputs!B17*B2 | C7: =Inputs!B17*C2 | D7: =Inputs!B17*D2 | E7: =Inputs!B17*E2 | F7: =Inputs!B17*F2
A8: G&A ($) | B8: =Inputs!B18*B2 | C8: =Inputs!B18*C2 | D8: =Inputs!B18*D2 | E8: =Inputs!B18*E2 | F8: =Inputs!B18*F2
A9: EBITDA ($) | B9: =B5-B6-B7-B8 | C9: =C5-C6-C7-C8 | D9: =D5-D6-D7-D8 | E9: =E5-E6-E7-E8 | F9: =F5-F6-F7-F8
A10: D&A ($) | B10: =Inputs!B19*B2 | C10: =Inputs!B19*C2 | D10: =Inputs!B19*D2 | E10: =Inputs!B19*E2 | F10: =Inputs!B19*F2
A11: EBIT ($) | B11: =B9-B10 | C11: =C9-C10 | D11: =D9-D10 | E11: =E9-E10 | F11: =F9-F10
A12: EBIT Margin % | B12: =IFERROR(B11/B2,"") | C12: =IFERROR(C11/C2,"") | D12: =IFERROR(D11/D2,"") | E12: =IFERROR(E11/E2,"") | F12: =IFERROR(F11/F2,"")
A13: Capex ($) | B13: =Inputs!B20*B2 | C13: =Inputs!B20*C2 | D13: =Inputs!B20*D2 | E13: =Inputs!B20*E2 | F13: =Inputs!B20*F2
A14: NWC ($) | B14: =Inputs!B21*B2 | C14: =Inputs!B21*C2 | D14: =Inputs!B21*D2 | E14: =Inputs!B21*E2 | F14: =Inputs!B21*F2
A15: ΔNWC ($) | B15: =B14-Inputs!B21*Inputs!B9 | C15: =C14-B14 | D15: =D14-C14 | E15: =E14-D14 | F15: =F14-E14
A16: FCFF ($) | B16: =B11*(1-Inputs!B6)+B10-B13-B15 | C16: =C11*(1-Inputs!B6)+C10-C13-C15 | D16: =D11*(1-Inputs!B6)+D10-D13-D15 | E16: =E11*(1-Inputs!B6)+E10-E13-E15 | F16: =F11*(1-Inputs!B6)+F10-F13-F15

Sheet DCF
A1: Item | B1: Value | C1: Notes
A2: WACC | B2: =Inputs!B7
A3: Terminal growth (g) | B3: =Inputs!B8
A4: Net Debt (Debt - Cash) | B4: =Inputs!B5 | C4: Negative = net cash (adds to equity)
A5: Diluted Shares (mm) | B5: =Inputs!B4
A6: FCFF Y1 | B6: =Forecast!B16
A7: FCFF Y2 | B7: =Forecast!C16
A8: FCFF Y3 | B8: =Forecast!D16
A9: FCFF Y4 | B9: =Forecast!E16
A10: FCFF Y5 | B10: =Forecast!F16
A11: Discount factor Y1 | B11: =1/(1+B2)^1
A12: DF Y2 | B12: =1/(1+B2)^2
A13: DF Y3 | B13: =1/(1+B2)^3
A14: DF Y4 | B14: =1/(1+B2)^4
A15: DF Y5 | B15: =1/(1+B2)^5
A16: PV Y1 | B16: =B5*B10
A17: PV Y2 | B17: =B6*B11
A18: PV Y3 | B18: =B7*B12
A19: PV Y4 | B19: =B8*B13
A20: PV Y5 | B20: =B9*B14
A21: Terminal Value (at Y5) | B21: =B9*(1+B3)/(B2-B3) | C21: Gordon growth, using FCFF5 next year method
A22: PV of Terminal | B22: =B20*B14
A23: Enterprise Value (EV) | B23: =SUM(B15:B19)+B21 | C23: PV of explicit + PV of terminal
A24: Equity Value ($M) | B24: =B22 - B4 | C24: EV - Net Debt
A25: Equity Value / Share ($) | B25: =B23/B5

Sheet Sensitivity
A1: WACC vs g (Equity value per share)
A2: g ↓ / WACC → | B2: 0.08 | C2: 0.09 | D2: 0.1 | E2: 0.11 | F2: 0.12 | G2: 0.13 | H2: 0.14
A3: 0.01 | B3: =(Forecast!B16/(1+B2)^1 + Forecast!C16/(1+B2)^2 + Forecast!D16/(1+B2)^3 + Forecast!E16/(1+B2)^4 + Forecast!F16/(1+B2)^5 + (Forecast!F16*(1+A3)/(B2-A3))/(1+B2)^5 - Inputs!B5) / Inputs!B4 | C3: =(Forecast!B16/(1+C2)^1 + Forecast!C16/(1+C2)^2 + Forecast!D16/(1+C2)^3 + Forecast!E16/(1+C2)^4 + Forecast!F16/(1+C2)^5 + (Forecast!F16*(1+A3)/(C2-A3))/(1+C2)^5 - Inputs!B5) / Inputs!B4 | D3: =(Forecast!B16/(1+D2)^1 + Forecast!C16/(1+D2)^2 + Forecast!D16/(1+D2)^3 + Forecast!E16/(1+D2)^4 + Forecast!F16/(1+D2)^5 + (Forecast!F16*(1+A3)/(D2-A3))/(1+D2)^5 - Inputs!B5) / Inputs!B4 | E3: =(Forecast!B16/(1+E2)^1 + Forecast!C16/(1+E2)^2 + Forecast!D16/(1+E2)^3 + Forecast!E16/(1+E2)^4 + Forecast!F16/(1+E2)^5 + (Forecast!F16*(1+A3)/(E2-A3))/(1+E2)^5 - Inputs!B5) / Inputs!B4 | F3: =(Forecast!B16/(1+F2)^1 + Forecast!C16/(1+F2)^2 + Forecast!D16/(1+F2)^3 + Forecast!E16/(1+F2)^4 + Forecast!F16/(1+F2)^5 + (Forecast!F16*(1+A3)/(F2-A3))/(1+F2)^5 - Inputs!B5) / Inputs!B4 | G3: =(Forecast!B16/(1+G2)^1 + Forecast!C16/(1+G2)^2 + Forecast!D16/(1+G2)^3 + Forecast!E16/(1+G2)^4 + Forecast!F16/(1+G2)^5 + (Forecast!F16*(1+A3)/(G2-A3))/(1+G2)^5 - Inputs!B5) / Inputs!B4 | H3: =(Forecast!B16/(1+H2)^1 + Forecast!C16/(1+H2)^2 + Forecast!D16/(1+H2)^3 + Forecast!E16/(1+H2)^4 + Forecast!F16/(1+H2)^5 + (Forecast!F16*(1+A3)/(H2-A3))/(1+H2)^5 - Inputs!B5) / Inputs!B4
A4: 0.02 | B4: =(Forecast!B16/(1+B2)^1 + Forecast!C16/(1+B2)^2 + Forecast!D16/(1+B2)^3 + Forecast!E16/(1+B2)^4 + Forecast!F16/(1+B2)^5 + (Forecast!F16*(1+A4)/(B2-A4))/(1+B2)^5 - Inputs!B5) / Inputs!B4 | C4: =(Forecast!B16/(1+C2)^1 + Forecast!C16/(1+C2)^2 + Forecast!D16/(1+C2)^3 + Forecast!E16/(1+C2)^4 + Forecast!F16/(1+C2)^5 + (Forecast!F16*(1+A4)/(C2-A4))/(1+C2)^5 - Inputs!B5) / Inputs!B4 | D4: =(Forecast!B16/(1+D2)^1 + Forecast!C16/(1+D2)^2 + Forecast!D16/(1+D2)^3 + Forecast!E16/(1+D2)^4 + Forecast!F16/(1+D2)^5 + (Forecast!F16*(1+A4)/(D2-A4))/(1+D2)^5 - Inputs!B5) / Inputs!B4 | E4: =(Forecast!B16/(1+E2)^1 + Forecast!C16/(1+E2)^2 + Forecast!D16/(1+E2)^3 + Forecast!E16/(1+E2)^4 + Forecast!F16/(1+E2)^5 + (Forecast!F16*(1+A4)/(E2-A4))/(1+E2)^5 - Inputs!B5) / Inputs!B4 | F4: =(Forecast!B16/(1+F2)^1 + Forecast!C16/(1+F2)^2 + Forecast!D16/(1+F2)^3 + Forecast!E16/(1+F2)^4 + Forecast!F16/(1+F2)^5 + (Forecast!F16*(1+A4)/(F2-A4))/(1+F2)^5 - Inputs!B5) / Inputs!B4 | G4: =(Forecast!B16/(1+G2)^1 + Forecast!C16/(1+G2)^2 + Forecast!D16/(1+G2)^3 + Forecast!E16/(1+G2)^4 + Forecast!F16/(1+G2)^5 + (Forecast!F16*(1+A4)/(G2-A4))/(1+G2)^5 - Inputs!B5) / Inputs!B4 | H4: =(Forecast!B16/(1+H2)^1 + Forecast!C16/(1+H2)^2 + Forecast!D16/(1+H2)^3 + Forecast!E16/(1+H2)^4 + Forecast!F16/(1+H2)^5 + (Forecast!F16*(1+A4)/(H2-A4))/(1+H2)^5 - Inputs!B5) / Inputs!B4
A5: 0.03 | B5: =(Forecast!B16/(1+B2)^1 + Forecast!C16/(1+B2)^2 + Forecast!D16/(1+B2)^3 + Forecast!E16/(1+B2)^4 + Forecast!F16/(1+B2)^5 + (Forecast!F16*(1+A5)/(B2-A5))/(1+B2)^5 - Inputs!B5) / Inputs!B4 | C5: =(Forecast!B16/(1+C2)^1 + Forecast!C16/(1+C2)^2 + Forecast!D16/(1+C2)^3 + Forecast!E16/(1+C2)^4 + Forecast!F16/(1+C2)^5 + (Forecast!F16*(1+A5)/(C2-A5))/(1+C2)^5 - Inputs!B5) / Inputs!B4 | D5: =(Forecast!B16/(1+D2)^1 + Forecast!C16/(1+D2)^2 + Forecast!D16/(1+D2)^3 + Forecast!E16/(1+D2)^4 + Forecast!F16/(1+D2)^5 + (Forecast!F16*(1+A5)/(D2-A5))/(1+D2)^5 - Inputs!B5) / Inputs!B4 | E5: =(Forecast!B16/(1+E2)^1 + Forecast!C16/(1+E2)^2 + Forecast!D16/(1+E2)^3 + Forecast!E16/(1+E2)^4 + Forecast!F16/(1+E2)^5 + (Forecast!F16*(1+A5)/(E2-A5))/(1+E2)^5 - Inputs!B5) / Inputs!B4 | F5: =(Forecast!B16/(1+F2)^1 + Forecast!C16/(1+F2)^2 + Forecast!D16/(1+F2)^3 + Forecast!E16/(1+F2)^4 + Forecast!F16/(1+F2)^5 + (Forecast!F16*(1+A5)/(F2-A5))/(1+F2)^5 - Inputs!B5) / Inputs!B4 | G5: =(Forecast!B16/(1+G2)^1 + Forecast!C16/(1+G2)^2 + Forecast!D16/(1+G2)^3 + Forecast!E16/(1+G2)^4 + Forecast!F16/(1+G2)^5 + (Forecast!F16*(1+A5)/(G2-A5))/(1+G2)^5 - Inputs!B5) / Inputs!B4 | H5: =(Forecast!B16/(1+H2)^1 + Forecast!C16/(1+H2)^2 + Forecast!D16/(1+H2)^3 + Forecast!E16/(1+H2)^4 + Forecast!F16/(1+H2)^5 + (Forecast!F16*(1+A5)/(H2-A5))/(1+H2)^5 - Inputs!B5) / Inputs!B4
A6: 0.04 | B6: =(Forecast!B16/(1+B2)^1 + Forecast!C16/(1+B2)^2 + Forecast!D16/(1+B2)^3 + Forecast!E16/(1+B2)^4 + Forecast!F16/(1+B2)^5 + (Forecast!F16*(1+A6)/(B2-A6))/(1+B2)^5 - Inputs!B5) / Inputs!B4 | C6: =(Forecast!B16/(1+C2)^1 + Forecast!C16/(1+C2)^2 + Forecast!D16/(1+C2)^3 + Forecast!E16/(1+C2)^4 + Forecast!F16/(1+C2)^5 + (Forecast!F16*(1+A6)/(C2-A6))/(1+C2)^5 - Inputs!B5) / Inputs!B4 | D6: =(Forecast!B16/(1+D2)^1 + Forecast!C16/(1+D2)^2 + Forecast!D16/(1+D2)^3 + Forecast!E16/(1+D2)^4 + Forecast!F16/(1+D2)^5 + (Forecast!F16*(1+A6)/(D2-A6))/(1+D2)^5 - Inputs!B5) / Inputs!B4 | E6: =(Forecast!B16/(1+E2)^1 + Forecast!C16/(1+E2)^2 + Forecast!D16/(1+E2)^3 + Forecast!E16/(1+E2)^4 + Forecast!F16/(1+E2)^5 + (Forecast!F16*(1+A6)/(E2-A6))/(1+E2)^5 - Inputs!B5) / Inputs!B4 | F6: =(Forecast!B16/(1+F2)^1 + Forecast!C16/(1+F2)^2 + Forecast!D16/(1+F2)^3 + Forecast!E16/(1+F2)^4 + Forecast!F16/(1+F2)^5 + (Forecast!F16*(1+A6)/(F2-A6))/(1+F2)^5 - Inputs!B5) / Inputs!B4 | G6: =(Forecast!B16/(1+G2)^1 + Forecast!C16/(1+G2)^2 + Forecast!D16/(1+G2)^3 + Forecast!E16/(1+G2)^4 + Forecast!F16/(1+G2)^5 + (Forecast!F16*(1+A6)/(G2-A6))/(1+G2)^5 - Inputs!B5) / Inputs!B4 | H6: =(Forecast!B16/(1+H2)^1 + Forecast!C16/(1+H2)^2 + Forecast!D16/(1+H2)^3 + Forecast!E16/(1+H2)^4 + Forecast!F16/(1+H2)^5 + (Forecast!F16*(1+A6)/(H2-A6))/(1+H2)^5 - Inputs!B5) / Inputs!B4
A7: 0.05 | B7: =(Forecast!B16/(1+B2)^1 + Forecast!C16/(1+B2)^2 + Forecast!D16/(1+B2)^3 + Forecast!E16/(1+B2)^4 + Forecast!F16/(1+B2)^5 + (Forecast!F16*(1+A7)/(B2-A7))/(1+B2)^5 - Inputs!B5) / Inputs!B4 | C7: =(Forecast!B16/(1+C2)^1 + Forecast!C16/(1+C2)^2 + Forecast!D16/(1+C2)^3 + Forecast!E16/(1+C2)^4 + Forecast!F16/(1+C2)^5 + (Forecast!F16*(1+A7)/(C2-A7))/(1+C2)^5 - Inputs!B5) / Inputs!B4 | D7: =(Forecast!B16/(1+D2)^1 + Forecast!C16/(1+D2)^2 + Forecast!D16/(1+D2)^3 + Forecast!E16/(1+D2)^4 + Forecast!F16/(1+D2)^5 + (Forecast!F16*(1+A7)/(D2-A7))/(1+D2)^5 - Inputs!B5) / Inputs!B4 | E7: =(Forecast!B16/(1+E2)^1 + Forecast!C16/(1+E2)^2 + Forecast!D16/(1+E2)^3 + Forecast!E16/(1+E2)^4 + Forecast!F16/(1+E2)^5 + (Forecast!F16*(1+A7)/(E2-A7))/(1+E2)^5 - Inputs!B5) / Inputs!B4 | F7: =(Forecast!B16/(1+F2)^1 + Forecast!C16/(1+F2)^2 + Forecast!D16/(1+F2)^3 + Forecast!E16/(1+F2)^4 + Forecast!F16/(1+F2)^5 + (Forecast!F16*(1+A7)/(F2-A7))/(1+F2)^5 - Inputs!B5) / Inputs!B4 | G7: =(Forecast!B16/(1+G2)^1 + Forecast!C16/(1+G2)^2 + Forecast!D16/(1+G2)^3 + Forecast!E16/(1+G2)^4 + Forecast!F16/(1+G2)^5 + (Forecast!F16*(1+A7)/(G2-A7))/(1+G2)^5 - Inputs!B5) / Inputs!B4 | H7: =(Forecast!B16/(1+H2)^1 + Forecast!C16/(1+H2)^2 + Forecast!D16/(1+H2)^3 + Forecast!E16/(1+H2)^4 + Forecast!F16/(1+H2)^5 + (Forecast!F16*(1+A7)/(H2-A7))/(1+H2)^5 - Inputs!B5) / Inputs!B4
A9: Grid recomputes DCF using each WACC,g pair. Edit Inputs to change assumptions.

Sheet Comps
A1: Ticker | B1: EV/EBITDA (NTM) | C1: P/E (NTM) | D1: Notes
A2: HOOD | B2: 63 | C2: 71 | D2: Enter market multiples (NTM)
A3: SCHW | B3: 36 | C3: 18.2 | D3: Enter market multiples (NTM)
A4: IBKR | B4: 33 | C4: 32.3 | D4: Enter market multiples (NTM)
A5: COIN | B5: 24.6 | C5: 54 | D5: Enter market multiples (NTM)
A6: SOFI | C6: 47 | D6: Enter market multiples (NTM)
A8: Select Forecast Year for Comps (1=Y1, 2=Y2, etc.) | B8: 2 | C8: Use Y2 to proxy NTM
A10: Derived metrics | B10: =INDEX(Forecast!B9:F9,1,B8)
A11: EBITDA (selected year) | B11: =Inputs!B4 | D11: =INDEX(Forecast!B9:F9, 1, B8)
A12: Net Income (proxy) | B12: =Inputs!B5 | D12: =INDEX(Forecast!B11:F11, 1, B8)*(1-Inputs!B6)
A13: Shares (mm) | B13: =MEDIAN(B2:B6)
A14: Net Debt ($M) | B14: =IF(INDEX(Forecast!B9:F9,1,B8)<=0,"",B13*INDEX(Forecast!B9:F9,1,B8))
B15: =IF(B14="","",B14 - B12)
A16: Implied Price from EV/EBITDA | B16: =IF(AND(B15<>"",B11>0),B15/B11,"")
A17: Median EV/EBITDA | B17: =MEDIAN(B2:B6)
A18: Implied EV (median) | B18: =MEDIAN(C2:C6)
A19: Implied Equity ($M) | B19: =IF(INDEX(Forecast!B11:F11,1,B8)*(1-Inputs!B6)<=0,"",B18*INDEX(Forecast!B11:F11,1,B8)*(1-Inputs!B6))
A20: Implied Price / share | B20: =IF(AND(B19<>"",B11>0),B19/B11,"")
A22: Implied Price from P/E
A23: Median P/E | B23: =MEDIAN(C2:C6)
A24: Implied Market Cap | B24: =B18*B10
A25: Implied Price / share | B25: =B19/B11

Sheet Valuation_Summary
A1: Valuation Output | B1: Value | C1: Notes
A2: DCF Equity / Share | B2: =DCF!B24 | C2: From base WACC,g in DCF sheet
A3: Comps (EV/EBITDA) Price | B3: =IF(Comps!B16="","",Comps!B16) | C3: Median EV/EBITDA → price
A4: Comps (P/E) Price | B4: =IF(Comps!B20="","",Comps!B20) | C4: Median P/E → price
A5: Comps Median Price | B5: =IF(COUNT(B3:B4)=0,"",MEDIAN(B3:B4))
B6: =IF(B2="","",IF(B5="",B2,AVERAGE(B2,B5)))
A7: Triangulated Target Price | B7: =AVERAGE(B2,B5) | C7: Average of DCF & comps median
A8: Upside vs Current Price | C8: Enter spot price below
A9: Current Price (manual) | B9: =IF(AND(B8>0,B6<>""),(B6-B8)/B8,"")
A10: Upside % | B10: =IF(B8>0,(B6-B8)/B8,"")

Sheet Initiation_OnePager
A1: Initiation — Robinhood Markets (HOOD): DCF & Comps Summary
A3: ="Call: Target Price = $" & TEXT(Valuation_Summary!B6, "0.00") & " (DCF $" & TEXT(Valuation_Summary!B2,"0.00") & ", Comps $" & TEXT(Valuation_Summary!B5,"0.00") & ")"
A5: Thesis (3 bullets):
A6: • Scalable brokerage platform with improving unit economics; operating leverage as S&M intensity normalizes.
A7: • Product expansion (options, futures, credit card/Gold) increases ARPU and retention; cash yields support NII tailwind.
A8: • Strong net cash; optionality for buybacks or M&A as profitability stabilizes.
A10: Catalysts:
A11: • Feature launches / cross-sell attach; MAU growth re-acceleration.
A12: • Margin expansion vs. guide; opex discipline; SBC trending down.
A13: • Macro rate path stabilizing; sustained net interest revenue.
A15: Key risks:
A16: • Regulatory changes (payment-for-order-flow, crypto).
A17: • Volatility in trading volumes; MAU churn.
A18: • Competitive response from incumbents / new entrants.
A20: Model snapshot (Y2 proxy for NTM):
A21: ="Revenue: $" & TEXT(Forecast!C2,"#,##0") & "M | EBITDA: $" & TEXT(Forecast!C9,"#,##0") & "M | EBIT margin: " & TEXT(Forecast!C12,"0.0%")
A23: Valuation cross-check:
A24: ="DCF $" & IF(Valuation_Summary!B2="","-",TEXT(Valuation_Summary!B2,"0.00")) & " | EV/EBITDA $" & IF(Valuation_Summary!B3="","-",TEXT(Valuation_Summary!B3,"0.00")) & " | P/E $" & IF(Valuation_Summary!B4="","-",TEXT(Valuation_Summary!B4,"0.00"))
A26: Export this sheet to PDF for your portfolio. Update Inputs and Comps to refresh.

Sheet Guide
A1: How to use this model (5–10 minutes):
A2: 1) Inputs: replace starting revenue, growth %, margins, capex, ΔNWC, shares, and net debt with real data/consensus.
A3: 2) Forecast: 5-year driver-based build; FCFF = EBIT(1–t) + D&A – Capex – ΔNWC.
A4: 3) DCF: discounts FCFF at WACC; terminal via Gordon growth on Year 5 FCFF. Equity = EV – Net Debt; per share = divide by diluted shares.
A5: 4) Sensitivity: WACC × terminal g grid returns equity value per share for quick triangulation.
A6: 5) Comps: paste NTM EV/EBITDA & P/E for HOOD + peers (SCHW, IBKR, COIN, SOFI). Pick Y2 for NTM proxy.
A7: 6) Valuation_Summary: averages DCF and comps median to a target price; type current price to show upside %.
A8: 7) Initiation_OnePager: auto-fills call, key numbers, thesis/catalysts/risks bullets ready for PDF export.
A9: Notes: For banks (e.g., JPM), analysts often prefer dividend discount/residual income. For HOOD/fintech, EV-based DCF is standard enough for portfolio work.
