Workbook

Sheet Guide_&_Sources
A1: Credit Risk Brief & Stress Test — JPM (FY2024)
A3: How bank GAAP maps to this corporate-style model:
A4: Item | B4: Source mapping | C4: Notes
A5: Revenue (model) | B5: JPM 'Total net revenue' (net interest income + noninterest revenue). | C5: Already net of deposit/loan interest.
A6: COGS/COF | B6: Set to 0. | C6: Avoid double-counting interest.
A7: SG&A | B7: Noninterest expense less D&A. | C7: Keeps D&A separate for EBITDA.
A8: D&A | B8: Cash flow statement 'depreciation & amortization'.
A9: Interest (coverage) | B9: LT debt × avg modified rate. | C9: Illustrative; deposit interest already netted.
A10: Cash | B10: Cash and due from banks + deposits with banks.
A11: Debt (ST/LT) | B11: Short‑term borrowings; Long‑term debt.
A13: Default stress (matches résumé)
A14: • Revenue −10%, funding +200 bps on % floating LT debt, +5 days DSO & DIO, ΔDPO = 0
A16: Auto pointers (read these):
A17: Base ND/EBITDA (x) | B17: =Base_Financials!B26 -> 429273.55 | C17: <3.5x typical corporate covenant
A18: Base EBITDA/Interest (x) | B18: =Base_Financials!B27 -> 5.5733908 | C18: LT‑debt only coverage
A19: Stressed FCF proxy ($M) | B19: =Stress_Results!B19 -> 2397.006
A20: Stressed ND/EBITDA (x) | B20: =Stress_Results!B21 -> 429273.55
A21: Stressed EBITDA/Interest (x) | B21: =Stress_Results!B22 -> 5.4714381
A22: Liquidity proxy ($M) | B22: =Covenants!D4 -> -17855.546 | C22: Cash + undrawn (revolver=0)
A24: Primary sources (FY2024) — copy into your memo
A25: Item | B25: Reference summary
A26: Total net revenue $177,556M; net income $58,471M; total assets $4,002,814M | B26: 2024 Annual Report / 2024 Form 10‑K summary
A27: Total noninterest expense $91,797M | B27: 2024 Form 10‑K, MD&A (three‑year summary)
A28: Cash $23,372M; Deposits with banks $445,945M; total $469,317M | B28: 2024 Form 10‑K, Consolidated BS & Cash Flows
A29: Short‑term borrowings $52,893M; Long‑term debt $401,418M | B29: 2024 Form 10‑K, Consolidated BS
A30: Weighted‑avg modified rate on LT debt ~5.15% | B30: 2024 Form 10‑K, Long‑term debt note
A31: D&A ≈ $7,938M (annual) | B31: Cash Flow statement / corroborated by Macrotrends/FinanceCharts
A32: Effective tax rate ≈ 22% | B32: 4Q24 Earnings Supplement (effective tax rate table)
A33: 2024 net revenue includes ~$7.9B Visa gain | B33: 2024 Annual Report note

Sheet Assumptions
A1: Key | B1: Value | C1: Notes
A2: Company | B2: JPMorgan Chase & Co. (JPM) — FY2024 baseline | C2: Replace if you want a different firm/year
A3: Fiscal Year | B3: 2024
A4: Currency | B4: USD (millions) | C4: Enter values in $M
A5: Tax Rate | B5: 0.221 | C5: Effective FY2024 (approx)
A6: Avg Interest Rate on Debt | B6: 0.0515 | C6: Weighted‑avg modified rate on LT debt
A7: % Floating Debt | B7: 0.4 | C7: Share of LT debt assumed floating (illustrative)
A8: SG&A Variable % | B8: 0.3 | C8: Portion flexing with revenue (illustrative)
A9: Capex % of Revenue | B9: 0.015 | C9: Proxy
A10: DSO (days) | B10: 35 | C10: Illustrative for receivables‑like assets
A11: DIO (days) | B11: 10 | C11: Low for banks; set to 0–10
A12: DPO (days) | B12: 20
A13: Min Cash Target | B13: 10000 | C13: $M buffer
A14: Revolver Capacity | B14: 0 | C14: Not applicable to banks
A15: Revolver Drawn | B15: 0 | C15: Not applicable to banks
A16: Revenue | B16: 177556 | C16: Total net revenue (GAAP)
A17: COGS/COF (Cost of Funds) | B17: 0 | C17: Net revenue already nets deposit/loan interest
A18: SG&A | B18: 83859 | C18: Noninterest expense (91,797) less D&A to avoid double count
A19: Other OpEx | B19: 0 | C19: Included in noninterest expense above
A20: D&A | B20: 7938 | C20: Depreciation & amortization (annual)
A21: Cash | B21: 469317 | C21: Cash + Deposits with banks (consolidated)
A22: Debt - Short Term | B22: 52893 | C22: Short‑term borrowings
A23: Debt - Long Term | B23: 401418 | C23: Long‑term debt

Sheet Base_Financials
A1: Metric | B1: Value | C1: Notes
A2: Revenue | B2: =Assumptions!B16 -> 177556
A3: COGS/COF | B3: =Assumptions!B17 -> 0
A4: Gross Profit | B4: =B2-B3 -> 177556 | C4: (= Revenue because COF=0 for banks)
A5: SG&A | B5: =Assumptions!B18 -> 83859
A6: Other OpEx | B6: =Assumptions!B19 -> 0
A7: EBITDA | B7: =B4-B5-B6 -> 93697
A8: D&A | B8: =Assumptions!B20 -> 7938
A9: EBIT | B9: =B7-B8 -> 85759
A10: Interest Expense (LT debt only) | B10: =Assumptions!B23*Assumptions!B6 -> 20673.027 | C10: Illustrative coverage metric
A11: EBT | B11: =B9-B10 -> 65085.973
A12: Taxes | B12: =B11*Assumptions!B5 -> 14384
A13: Net Income | B13: =B11-B12 -> 50701.973
A14: NOPAT | B14: =B9*(1-Assumptions!B5) -> 66806.261
A15: Capex | B15: =Assumptions!B9*B2 -> 2663.34
A16: AR (from DSO) | B16: =B2/365*Assumptions!B10 -> 17025.918
A17: Inventory (from DIO) | B17: =B3/365*Assumptions!B11 -> 0
A18: AP (from DPO) | B18: =B3/365*Assumptions!B12 -> 0
A19: NWC | B19: =B15+B16-B17 -> 19689.258
A20: ΔNWC (YTD proxy) | B20: =B18 -> 0
A21: FCF (proxy) | B21: =B13 + B8 - B14 - B19 -> -27855.546 | C21: NOPAT + D&A - Capex - ΔNWC
A22: Cash | B22: =Assumptions!B21 -> 469317
A23: Debt - ST | B23: =Assumptions!B22 -> 52893
A24: Debt - LT | B24: =Assumptions!B23 -> 401418
A25: Total Debt | B25: =B22+B23 -> 522210
A26: Net Debt | B26: =B24-B21 -> 429273.55
A27: Net Debt / EBITDA | B27: =IF(B7=0,"",B25/B7) -> 5.5733908
A28: EBITDA / Interest | B28: =IF(B10=0,"",B7/B10) -> 4.5323309
A29: EBIT / Interest | B29: =IF(B10=0,"",B9/B10) -> 4.1483523
A30: Current Assets (Cash+AR+Inv) | B30: =B21+B15+B16 -> -8166.288
A31: Current Liabilities (AP+ST Debt) | B31: =B17+B22 -> 469317
A32: Current Ratio | B32: =IF(B29=0,"",B28/B29) -> 1.0925617
A33: Quick Ratio | B33: =IF(B29=0,"",(B21+B15)/B29) -> -6072.8221

Sheet Stress_Input
A1: Parameter | B1: Value | C1: Notes
A2: Revenue Shock % | B2: -0.1 | C2: -10% revenue (résumé default)
A3: Funding Cost +bps | B3: 200 | C3: +200 bps on % floating LT debt
A4: Δ DSO (days) | B4: 5
A5: Δ DIO (days) | B5: 5
A6: Δ DPO (days) | B6: 0
A7: SG&A Variable % Override | C7: blank = use Assumptions

Sheet Stress_Results
A1: Metric | B1: Stressed Value | C1: Notes
A2: Revenue (stressed) | B2: =N(Base_Financials!B2)*(1+N(Stress_Input!B2)) -> 159800.4
A3: COGS/COF (stressed) | B3: =IFERROR(N(Base_Financials!B3)/N(Base_Financials!B2)*B2,0) -> 0 | C3: Hold base % (0 for banks)
A4: SG&A (stressed) | B4: =N(Base_Financials!B5)*( (IF(ISNUMBER(Stress_Input!B7),N(Stress_Input!B7),N(Assumptions!B8)))*(B2/N(Base_Financials!B2)) + (1-IF(ISNUMBER(Stress_Input!B7),N(Stress_Input!B7),N(Assumptions!B8)))) -> 81343.23 | C4: Variable share scales with revenue; fixed share stays flat
A5: Other OpEx (stressed) | B5: =N(Base_Financials!B6) -> 0
A6: EBITDA (stressed) | B6: =B2-B3-B4-B5 -> 78457.17
A7: D&A (stressed) | B7: =N(Base_Financials!B8) -> 7938
A8: EBIT (stressed) | B8: =B6-B7 -> 70519.17
A9: Interest Expense (stressed) | B9: =(N(Assumptions!B6) + (N(Stress_Input!B3)/10000)*N(Assumptions!B7)) * N(Base_Financials!B25) -> 31071.495 | C9: Shock only on floating LT debt
A10: EBT (stressed) | B10: =B8-B9 -> 39447.675
A11: Taxes (stressed) | B11: =B10*N(Assumptions!B5) -> 8717.9362
A12: Net Income (stressed) | B12: =B10-B11 -> 30729.739
A13: NOPAT (stressed) | B13: =B8*(1-N(Assumptions!B5)) -> 54934.433
A14: AR (stressed) | B14: =B2/365*(N(Assumptions!B10)+N(Stress_Input!B4)) -> 17512.373
A15: Inventory (stressed) | B15: =B3/365*(N(Assumptions!B11)+N(Stress_Input!B5)) -> 0
A16: AP (stressed) | B16: =B3/365*(N(Assumptions!B12)+N(Stress_Input!B6)) -> 0
A17: NWC (stressed) | B17: =B14+B15-B16 -> 17512.373
A18: ΔNWC (stressed) | B18: =B17 -> 17512.373
A19: Capex (stressed) | B19: =N(Assumptions!B9)*B2 -> 2397.006
A20: FCF (proxy, stressed) | B20: =B13+B7-B19-B18 -> 42963.055 | C20: NOPAT + D&A - Capex - ΔNWC
A21: Net Debt (base) | B21: =N(Base_Financials!B26) -> 429273.55
A22: Net Debt / EBITDA (stressed) | B22: =IFERROR(IF(N(B6)<=0,"", N(B21)/N(B6)), "") -> 5.4714381
A23: EBITDA/Interest (stressed) | B23: =IFERROR(IF(N(B9)<=0,"", N(B6)/N(B9)), "") -> 2.5250529
A24: EBIT/Interest (stressed) | B24: =IFERROR(IF(N(B9)<=0,"", N(B8)/N(B9)), "") -> 2.2695776

Sheet Covenants
A1: Covenant / Limit | B1: Threshold | C1: Base Metric | D1: Base Value | E1: Base Status | F1: Stressed Metric | G1: Stressed Value | H1: Stressed Status | I1: Notes
A2: Max Net Debt/EBITDA | B2: 3.5 | C2: Base: ND/EBITDA | D2: =Base_Financials!B26 -> 429273.55 | E2: =IF(D2<=B2,"PASS","FAIL") -> FAIL | F2: Stressed: ND/EBITDA | G2: =Stress_Results!B21 -> 429273.55 | H2: =IF(G2<=B2,"PASS","FAIL") -> FAIL | I2: Illustrative for a bank
A3: Min EBITDA/Interest | B3: 3 | C3: Base: EBITDA/Int | D3: =Base_Financials!B27 -> 5.5733908 | E3: =IF(D3>=B3,"PASS","FAIL") -> PASS | F3: Stressed: EBITDA/Int | G3: =Stress_Results!B22 -> 5.4714381 | H3: =IF(G3>=B3,"PASS","FAIL") -> PASS | I3: Uses LT‑debt interest only
A4: Min Liquidity ($M) | B4: 10000 | C4: Cash+Undrawn Rev (base) | D4: =Base_Financials!B21 + (Assumptions!B13-Assumptions!B14) -> -17855.546 | E4: =IF(D4>=B4,"PASS","FAIL") -> FAIL | F4: Cash+Undrawn Rev (stressed) | G4: =Base_Financials!B21 + (Assumptions!B13-Assumptions!B14) -> -17855.546 | H4: =IF(G4>=B4,"PASS","FAIL") -> FAIL | I4: Banks don't use revolvers; set to cash only

Sheet Brief
A1: Section | B1: Content
A2: Borrower & Facilities | B2: JPMorgan Chase & Co. (JPM). Funding via deposits (not modeled), short‑term borrowings and LT senior/structured notes. Purpose: liquidity/funding.
A3: Business & Financial Profile | B3: Rev ($M): =Base_Financials!B1 | EBITDA ($M): =Base_Financials!B6 | Net Debt ($M): =Base_Financials!B25
A4: Key Ratios (Base) | B4: ND/EBITDA: =Base_Financials!B26 | EBITDA/Int: =Base_Financials!B27 | Current Ratio: =Base_Financials!B30 (corporate proxy)
A5: Liquidity | B5: Cash ($M): =Base_Financials!B21 | Undrawn Rev ($M): =Assumptions!B13-Assumptions!B14
A6: Stress Scenario | B6: Rev shock: =Stress_Input!B2 ; +bps on floating LT debt: =Stress_Input!B3 ; ΔDSO: =Stress_Input!B4 ; ΔDIO: =Stress_Input!B5 ; ΔDPO: =Stress_Input!B6
A7: Stress Results — Headline | B7: FCF (stressed, $M): =Stress_Results!B19 | ND/EBITDA: =Stress_Results!B21 | EBITDA/Int: =Stress_Results!B22
A8: Interpretation & Mitigants | B8: Coverage uses LT‑debt interest only (deposit interest is netted in revenue). Mitigants: tighten risk limits; add collateral/pricing triggers; hedge rate exposure; monitor EWIs: coverage<3x, ND/EBITDA>3.5x, DSO/DIO creep, liquidity draw.
